dbc_editor/__init__.py
dbc_editor/__main__.py
dbc_editor/config.py
dbc_editor/main.py
dbc_editor/model_input_history.py
dbc_editor/runmodule.sh
dbc_editor/urwid_edit_with_history.py
dbc_editor-0.6.1.dist-info/entry_points.txt
dbc_editor-0.6.1.dist-info/LICENSE
dbc_editor-0.6.1.dist-info/WHEEL
dbc_editor-0.6.1.dist-info/METADATA
dbc_editor-0.6.1.dist-info/RECORD
