Metadata-Version: 2.1
Name: dbc-editor
Version: 0.6.1
Summary: An editor for CAN bus database files like dbc or sym, based on cantools and urwid
Author-email: erzo <erzo@posteo.de>
Requires-Python: >=3.7
Classifier: Operating System :: POSIX
Classifier: Operating System :: Unix
Classifier: Environment :: Console
Classifier: License :: OSI Approved :: BSD License
Requires-Dist: urwid <3
Requires-Dist: urwid_readline <0.16
Requires-Dist: cantools >=37.0.2,<=38.0.2
Project-URL: Bug tracker, https://gitlab.com/erzo/dbc-editor/-/issues
Project-URL: Change log, https://gitlab.com/erzo/dbc-editor/-/tags
Project-URL: Source code, https://gitlab.com/erzo/dbc-editor
